avatar_sdk/__init__.py
avatar_sdk/auth.py
avatar_sdk/avatar_client.py
avatar_sdk/config.py
avatar_sdk/config_loader.py
avatar_sdk/exceptions.py
avatar_sdk_python-1.0.5.dist-info/LICENSE
avatar_sdk_python-1.0.5.dist-info/METADATA
avatar_sdk_python-1.0.5.dist-info/WHEEL
avatar_sdk_python-1.0.5.dist-info/RECORD
