Metadata-Version: 2.3
Name: avatar-sdk-python
Version: 1.0.5
Summary: 讯飞虚拟人 Python SDK - 基于实时交互API的虚拟人交互SDK
License: MIT
Keywords: avatar,virtual,ai,sdk,iflytek,websocket
Author: thoulee
Author-email: thou_lee@outlook.com
Maintainer: thoulee
Maintainer-email: thou_lee@outlook.com
Requires-Python: >=3.9,<4.0
Classifier: Development Status :: 4 - Beta
Classifier: Intended Audience :: Developers
Classifier: License :: OSI Approved :: MIT License
Classifier: Programming Language :: Python :: 3
Classifier: Programming Language :: Python :: 3.9
Classifier: Programming Language :: Python :: 3.10
Classifier: Programming Language :: Python :: 3.11
Classifier: Programming Language :: Python :: 3.12
Classifier: Programming Language :: Python :: 3.13
Classifier: Topic :: Communications
Classifier: Topic :: Multimedia :: Video
Classifier: Topic :: Software Development :: Libraries :: Python Modules
Requires-Dist: python-dotenv (==1.0.0)
Requires-Dist: ws4py (>=0.5.1,<0.6.0)
Project-URL: Documentation, https://github.com/thoulee21/avatar-sdk-python#readme
Project-URL: Homepage, https://github.com/thoulee21/avatar-sdk-python
Project-URL: Repository, https://github.com/thoulee21/avatar-sdk-python
